MANIFEST.in
README.rst
setup.py
jpegtran/__init__.py
jpegtran/lib.py
jpegtran/transform.py
jpegtran/__pycache__/_cffi__xb366312fxf3ca0677.c
jpegtran/__pycache__/_cffi__xbfac4b5xcdb1023.c
jpegtran_cffi.egg-info/PKG-INFO
jpegtran_cffi.egg-info/SOURCES.txt
jpegtran_cffi.egg-info/dependency_links.txt
jpegtran_cffi.egg-info/not-zip-safe
jpegtran_cffi.egg-info/requires.txt
jpegtran_cffi.egg-info/top_level.txt
src/Epeg.h
src/epeg.c
src/epeg_private.h
src/jinclude.h
src/jpegint.h
src/jpegtran.c
src/jversion.h
src/transupp.c
src/transupp.h
test/test.jpg
test/test_thumb.jpg
test/test_transform.py