Metadata-Version: 1.0
Name: jpegtran-cffi
Version: 0.5.2
Summary: Extremly fast, (mostly) lossless JPEG transformations
Home-page: http://github.com/jbaiter/jpegtran-cffi.git
Author: Johannes Baiter
Author-email: johannes.baiter@gmail.com
License: MIT
Platform: UNKNOWN
